m_esh_v0-0.0.2.dist-info/METADATA
m_esh_v0-0.0.2.dist-info/WHEEL
m_esh_v0-0.0.2.dist-info/entry_points.txt
m_esh_v0-0.0.2.dist-info/licenses/LICENSE
m_esh_v0/__init__.py
m_esh_v0-0.0.2.dist-info/RECORD
