Metadata-Version: 2.1
Name: m_esh_v0
Version: 0.0.2
Summary: Default template for PDM package
Author-Email: lwmacct <lwmacct@icloud.com>
License: MIT
Requires-Python: >=3.12
